<?xml version="1.0" encoding="utf-8" ?>
<Module>

  <ModulePrefs author="Simon McNaughton" author_email="simon.mcnaughton@uqconnect.edu.au"
    description="LORE-Map" title="LORE-Map"  height="595" width= "500"/>

  <Content type="html" view="home, profile, preview"><![CDATA[	 
	 <script type="text/javascript" src="http://maps.google.com/maps/api/js?v=3.2&sensor=false"></script>
     
     <script type="text/javascript" src="./lib/jquery-1.7.2.min.js"></script>
     <script type="text/javascript" src="./lib/ext3.2/adapter/jquery/ext-jquery-adapter-debug.js"></script>
     <script type="text/javascript" src="./lib/ext3.2/ext-all.js"></script>
     
	 <script type="text/javascript" src="./lib/leaflet.js"></script>
     <script type="text/javascript" src="./lib/Google.js"></script>
     
     <script type="text/javascript" src="init.js"></script>
     
	 <link rel="stylesheet" type="text/css" href="./lib/ext3.2/resources/css/ext-all.css"/>
     <link rel="stylesheet" type="text/css" href="./lib/ext3.2/resources/css/xtheme-gray.css"/>
     <link rel="stylesheet" type="text/css" href="./lore_map.css"/>
	 <link rel="stylesheet" type="text/css" href="./leaflet.css" />
  ]]></Content>
</Module>
